applovin_report/__init__.py
applovin_report/revenue_reporting_api.py
applovin_report-0.2.1.dist-info/LICENSE
applovin_report-0.2.1.dist-info/METADATA
applovin_report-0.2.1.dist-info/WHEEL
applovin_report-0.2.1.dist-info/RECORD
